Opentsdb23ZhongwenWendang/README.md
Opentsdb23ZhongwenWendang/__init__.py
Opentsdb23ZhongwenWendang/__main__.py
Opentsdb23ZhongwenWendang/file.epub
Opentsdb23ZhongwenWendang/index.html
Opentsdb23ZhongwenWendang/css/__init__.py
Opentsdb23ZhongwenWendang/css/annotations.css
Opentsdb23ZhongwenWendang/css/main.css
Opentsdb23ZhongwenWendang/css/normalize.css
Opentsdb23ZhongwenWendang/css/popup.css
Opentsdb23ZhongwenWendang/font/__init__.py
Opentsdb23ZhongwenWendang/font/fontello.eot
Opentsdb23ZhongwenWendang/font/fontello.svg
Opentsdb23ZhongwenWendang/font/fontello.ttf
Opentsdb23ZhongwenWendang/font/fontello.woff
Opentsdb23ZhongwenWendang/img/__init__.py
Opentsdb23ZhongwenWendang/img/annotator-glyph-sprite.png
Opentsdb23ZhongwenWendang/img/annotator-icon-sprite.png
Opentsdb23ZhongwenWendang/img/apple-touch-icon.png
Opentsdb23ZhongwenWendang/img/cancelfullscreen.png
Opentsdb23ZhongwenWendang/img/close.png
Opentsdb23ZhongwenWendang/img/fullscreen.png
Opentsdb23ZhongwenWendang/img/loader.gif
Opentsdb23ZhongwenWendang/img/menu-icon.png
Opentsdb23ZhongwenWendang/img/save.png
Opentsdb23ZhongwenWendang/img/saved.png
Opentsdb23ZhongwenWendang/img/settings-s.png
Opentsdb23ZhongwenWendang/img/settings.png
Opentsdb23ZhongwenWendang/img/star.png
Opentsdb23ZhongwenWendang/js/__init__.py
Opentsdb23ZhongwenWendang/js/epub.js
Opentsdb23ZhongwenWendang/js/epub.min.js
Opentsdb23ZhongwenWendang/js/epub.min.map
Opentsdb23ZhongwenWendang/js/hooks.min.js
Opentsdb23ZhongwenWendang/js/hooks.min.map
Opentsdb23ZhongwenWendang/js/reader.js
Opentsdb23ZhongwenWendang/js/reader.js.map
Opentsdb23ZhongwenWendang/js/reader.min.js
Opentsdb23ZhongwenWendang/js/reader.min.map
Opentsdb23ZhongwenWendang/js/hooks/__init__.py
Opentsdb23ZhongwenWendang/js/hooks/extensions/__init__.py
Opentsdb23ZhongwenWendang/js/hooks/extensions/highlight.js
Opentsdb23ZhongwenWendang/js/libs/__init__.py
Opentsdb23ZhongwenWendang/js/libs/jquery.min.js
Opentsdb23ZhongwenWendang/js/libs/localforage.min.js
opentsdb_2_3_zhongwen_wendang-2024.3.5.0.dist-info/METADATA
opentsdb_2_3_zhongwen_wendang-2024.3.5.0.dist-info/WHEEL
opentsdb_2_3_zhongwen_wendang-2024.3.5.0.dist-info/entry_points.txt
opentsdb_2_3_zhongwen_wendang-2024.3.5.0.dist-info/top_level.txt
opentsdb_2_3_zhongwen_wendang-2024.3.5.0.dist-info/RECORD
